{"cameraMode":{"drawMode":0,"name":"Shaded","section":"Shading Mode"},"sceneLighting":false,"audioPlay":false,"sceneViewState":{"m_AlwaysRefresh":false,"showFog":true,"showSkybox":false,"showFlares":true,"showImageEffects":true,"showParticleSystems":true,"showVisualEffectGraphs":true,"m_FxEnabled":true},"in2DMode":false,"pivot":{"x":0.28999999165534975,"y":3.690000057220459,"z":-0.5},"rotation":{"x":0.020045708864927293,"y":0.29774579405784609,"z":-0.006254078820347786,"w":0.9544180631637573},"size":10.0,"orthographic":true}